madbg/__init__.py
madbg/__main__.py
madbg/api.py
madbg/client.py
madbg/communication.py
madbg/consts.py
madbg/debugger.py
madbg/tty_utils.py
madbg/utils.py
madbg-1.3.2.dist-info/LICENSE.txt
madbg-1.3.2.dist-info/METADATA
madbg-1.3.2.dist-info/WHEEL
madbg-1.3.2.dist-info/entry_points.txt
madbg-1.3.2.dist-info/top_level.txt
madbg-1.3.2.dist-info/RECORD
