Metadata-Version: 2.1
Name: madbg
Version: 1.3.2
Summary: A fully-featured remote debugger for python
Home-page: https://github.com/kmaork/madbg
Author: Maor Kleinberger
Author-email: kmaork@gmail.com
Keywords: debugger remote tty attach ipdb pdb debug
Classifier: Intended Audience :: Developers
Classifier: License :: OSI Approved :: MIT License
Classifier: Programming Language :: Python :: 3
Classifier: Programming Language :: Python :: 3 :: Only
Classifier: Programming Language :: Python :: 3.7
Classifier: Programming Language :: Python :: 3.8
Classifier: Programming Language :: Python :: 3.9
Classifier: Programming Language :: Python :: 3.10
Classifier: Programming Language :: Python :: 3.11
Classifier: Operating System :: POSIX :: Linux
Requires-Python: >=3.7
License-File: LICENSE.txt
Requires-Dist: click
Requires-Dist: IPython (>=7.17.0)
Requires-Dist: prompt-toolkit
Requires-Dist: hypno (>=0.1.3)
